distkv_ext/akumuli/__init__.py
distkv_ext/akumuli/_config.yaml
distkv_ext/akumuli/client.py
distkv_ext/akumuli/model.py
distkv_ext/akumuli/task.py
distkv_akumuli-0.7.3.dist-info/METADATA
distkv_akumuli-0.7.3.dist-info/WHEEL
distkv_akumuli-0.7.3.dist-info/top_level.txt
distkv_akumuli-0.7.3.dist-info/zip-safe
distkv_akumuli-0.7.3.dist-info/RECORD
